trytond/modules/account_de_skr03/__init__.py
trytond/modules/account_de_skr03/account_de.xml
trytond/modules/account_de_skr03/tax_de.xml
trytond/modules/account_de_skr03/tryton.cfg
trytond/modules/account_de_skr03/tests/__init__.py
trytond/modules/account_de_skr03/tests/test_module.py
trytond_account_de_skr03-7.8.0.dist-info/licenses/LICENSE
trytond_account_de_skr03-7.8.0.dist-info/METADATA
trytond_account_de_skr03-7.8.0.dist-info/WHEEL
trytond_account_de_skr03-7.8.0.dist-info/entry_points.txt
trytond_account_de_skr03-7.8.0.dist-info/top_level.txt
trytond_account_de_skr03-7.8.0.dist-info/RECORD
